pyLaysWebhooker/__init__.py
pyLaysWebhooker/main.py
pyLaysWebhooker-2.dist-info/METADATA
pyLaysWebhooker-2.dist-info/WHEEL
pyLaysWebhooker-2.dist-info/entry_points.txt
pyLaysWebhooker-2.dist-info/top_level.txt
pyLaysWebhooker-2.dist-info/RECORD
