Metadata-Version: 2.1
Name: pyLaysWebhooker
Version: 2
Requires-Dist: requests
